impressum_helvetica/collect_impressum.py
impressum_helvetica/hostnames.py
impressum_helvetica/settings.py
impressum_helvetica-0.1.2.dist-info/LICENSE
impressum_helvetica-0.1.2.dist-info/METADATA
impressum_helvetica-0.1.2.dist-info/WHEEL
impressum_helvetica-0.1.2.dist-info/RECORD
