Metadata-Version: 2.1
Name: impressum-helvetica
Version: 0.1.2
Summary: 
Author: alho94
Author-email: alexander.horst.ah@gmail.com
Requires-Python: >=3.10,<4.0
Classifier: Programming Language :: Python :: 3
Classifier: Programming Language :: Python :: 3.10
Classifier: Programming Language :: Python :: 3.11
Classifier: Programming Language :: Python :: 3.12
Requires-Dist: pillow (>=11.3.0,<12.0.0)
Requires-Dist: playwright (>=1.55.0,<2.0.0)
